[
  {"id": "e1", "text": "It always seems impossible until it's done.", "author": "Nelson Mandela", "category": "encouragement"},
  {"id": "e2", "text": "Believe you can and you're halfway there.", "author": "Theodore Roosevelt", "category": "encouragement"},
  {"id": "e3", "text": "You are braver than you believe, stronger than you seem, and smarter than you think.", "author": "A. A. Milne", "category": "encouragement"},
  {"id": "e4", "text": "The best way out is always through.", "author": "Robert Frost", "category": "encouragement"},
  {"id": "e5", "text": "Fall seven times, stand up eight.", "author": "Japanese Proverb", "category": "encouragement"},
  {"id": "e6", "text": "It does not matter how slowly you go as long as you do not stop.", "author": "Confucius", "category": "encouragement"},
  {"id": "e7", "text": "Success is not final, failure is not fatal: it is the courage to continue that counts.", "author": "Winston Churchill", "category": "encouragement"},
  {"id": "e8", "text": "The only way to do great work is to love what you do.", "author": "Steve Jobs", "category": "encouragement"},
  {"id": "e9", "text": "Our greatest glory is not in never falling, but in rising every time we fall.", "author": "Oliver Goldsmith", "category": "encouragement"},
  {"id": "e10", "text": "What lies behind us and what lies before us are tiny matters compared to what lies within us.", "author": "Ralph Waldo Emerson", "category": "encouragement"},
  {"id": "e11", "text": "Keep your face always toward the sunshine, and shadows will fall behind you.", "author": "Walt Whitman", "category": "encouragement"},
  {"id": "e12", "text": "You miss 100% of the shots you don't take.", "author": "Wayne Gretzky", "category": "encouragement"},
  {"id": "e13", "text": "Whether you think you can or you think you can't, you're right.", "author": "Henry Ford", "category": "encouragement"},
  {"id": "e14", "text": "Everything you've ever wanted is on the other side of fear.", "author": "George Addair", "category": "encouragement"},
  {"id": "e15", "text": "Hardships often prepare ordinary people for an extraordinary destiny.", "author": "C. S. Lewis", "category": "encouragement"},
  {"id": "e16", "text": "Start where you are. Use what you have. Do what you can.", "author": "Arthur Ashe", "category": "encouragement"},
  {"id": "e17", "text": "The future belongs to those who believe in the beauty of their dreams.", "author": "Eleanor Roosevelt", "category": "encouragement"},
  {"id": "e18", "text": "Act as if what you do makes a difference. It does.", "author": "William James", "category": "encouragement"},
  {"id": "e19", "text": "You are never too old to set another goal or to dream a new dream.", "author": "C. S. Lewis", "category": "encouragement"},
  {"id": "e20", "text": "Courage doesn't always roar. Sometimes courage is the quiet voice at the end of the day saying, 'I will try again tomorrow.'", "author": "Mary Anne Radmacher", "category": "encouragement"},
  {"id": "e21", "text": "A journey of a thousand miles begins with a single step.", "author": "Lao Tzu", "category": "encouragement"},
  {"id": "e22", "text": "When you have a dream, you've got to grab it and never let go.", "author": "Carol Burnett", "category": "encouragement"},
  {"id": "e23", "text": "Nothing is impossible. The word itself says 'I'm possible!'", "author": "Audrey Hepburn", "category": "encouragement"},
  {"id": "e24", "text": "If you're going through hell, keep going.", "author": "Winston Churchill", "category": "encouragement"},
  {"id": "e25", "text": "The only limit to our realization of tomorrow will be our doubts of today.", "author": "Franklin D. Roosevelt", "category": "encouragement"},
  {"id": "e26", "text": "Do what you can, with what you have, where you are.", "author": "Theodore Roosevelt", "category": "encouragement"},
  {"id": "e27", "text": "Perseverance is not a long race; it is many short races one after the other.", "author": "Walter Elliot", "category": "encouragement"},
  {"id": "e28", "text": "Tough times never last, but tough people do.", "author": "Robert H. Schuller", "category": "encouragement"},
  {"id": "e29", "text": "You have within you right now, everything you need to deal with whatever the world can throw at you.", "author": "Brian Tracy", "category": "encouragement"},
  {"id": "e30", "text": "Storms make trees take deeper roots.", "author": "Dolly Parton", "category": "encouragement"},
  {"id": "e31", "text": "The secret of getting ahead is getting started.", "author": "Mark Twain", "category": "encouragement"},
  {"id": "e32", "text": "I can't change the direction of the wind, but I can adjust my sails to always reach my destination.", "author": "Jimmy Dean", "category": "encouragement"},
  {"id": "e33", "text": "Believe in yourself and all that you are. Know that there is something inside you that is greater than any obstacle.", "author": "Christian D. Larson", "category": "encouragement"},
  {"id": "e34", "text": "Every strike brings me closer to the next home run.", "author": "Babe Ruth", "category": "encouragement"},
  {"id": "e35", "text": "Don't watch the clock; do what it does. Keep going.", "author": "Sam Levenson", "category": "encouragement"},
  {"id": "e36", "text": "The harder the conflict, the more glorious the triumph.", "author": "Thomas Paine", "category": "encouragement"},
  {"id": "e37", "text": "Optimism is the faith that leads to achievement. Nothing can be done without hope and confidence.", "author": "Helen Keller", "category": "encouragement"},
  {"id": "e38", "text": "Although the world is full of suffering, it is also full of the overcoming of it.", "author": "Helen Keller", "category": "encouragement"},
  {"id": "e39", "text": "In the middle of difficulty lies opportunity.", "author": "Albert Einstein", "category": "encouragement"},
  {"id": "e40", "text": "What you get by achieving your goals is not as important as what you become by achieving your goals.", "author": "Zig Ziglar", "category": "encouragement"},
  {"id": "e41", "text": "You don't have to see the whole staircase, just take the first step.", "author": "Martin Luther King Jr.", "category": "encouragement"},
  {"id": "e42", "text": "If you can dream it, you can do it.", "author": "Walt Disney", "category": "encouragement"},
  {"id": "e43", "text": "Turn your wounds into wisdom.", "author": "Oprah Winfrey", "category": "encouragement"},
  {"id": "e44", "text": "We may encounter many defeats but we must not be defeated.", "author": "Maya Angelou", "category": "encouragement"},
  {"id": "e45", "text": "You may not control all the events that happen to you, but you can decide not to be reduced by them.", "author": "Maya Angelou", "category": "encouragement"},
  {"id": "e46", "text": "The best time to plant a tree was 20 years ago. The second best time is now.", "author": "Chinese Proverb", "category": "encouragement"},
  {"id": "e47", "text": "When one door of happiness closes, another opens; but often we look so long at the closed door that we do not see the one which has been opened for us.", "author": "Helen Keller", "category": "encouragement"},
  {"id": "e48", "text": "It is never too late to be what you might have been.", "author": "George Eliot", "category": "encouragement"},
  {"id": "e49", "text": "Do not go where the path may lead, go instead where there is no path and leave a trail.", "author": "Ralph Waldo Emerson", "category": "encouragement"},
  {"id": "e50", "text": "The greatest glory in living lies not in never falling, but in rising every time we fall.", "author": "Nelson Mandela", "category": "encouragement"},
  {"id": "e51", "text": "Life is 10% what happens to us and 90% how we react to it.", "author": "Charles R. Swindoll", "category": "encouragement"},
  {"id": "e52", "text": "With the new day comes new strength and new thoughts.", "author": "Eleanor Roosevelt", "category": "encouragement"},
  {"id": "e53", "text": "Just when the caterpillar thought the world was ending, he turned into a butterfly.", "author": "Unknown", "category": "encouragement"},
  {"id": "e54", "text": "This too shall pass.", "author": "Unknown", "category": "encouragement"},
  {"id": "e55", "text": "Every day may not be good, but there is something good in every day.", "author": "Unknown", "category": "encouragement"},
  {"id": "e56", "text": "Difficult roads often lead to beautiful destinations.", "author": "Unknown", "category": "encouragement"},
  {"id": "e57", "text": "A smooth sea never made a skilled sailor.", "author": "Franklin D. Roosevelt", "category": "encouragement"},
  {"id": "e58", "text": "Don't count the days, make the days count.", "author": "Muhammad Ali", "category": "encouragement"},
  {"id": "e59", "text": "He who has a why to live can bear almost any how.", "author": "Friedrich Nietzsche", "category": "encouragement"},
  {"id": "e60", "text": "What doesn't kill us makes us stronger.", "author": "Friedrich Nietzsche", "category": "encouragement"},
  {"id": "e61", "text": "The wound is the place where the light enters you.", "author": "Rumi", "category": "encouragement"},
  {"id": "e62", "text": "Everything in the universe is within you. Ask all from yourself.", "author": "Rumi", "category": "encouragement"},
  {"id": "e63", "text": "Be yourself; everyone else is already taken.", "author": "Oscar Wilde", "category": "encouragement"},
  {"id": "e64", "text": "We are all in the gutter, but some of us are looking at the stars.", "author": "Oscar Wilde", "category": "encouragement"},
  {"id": "e65", "text": "Happiness can be found even in the darkest of times, if one only remembers to turn on the light.", "author": "J. K. Rowling", "category": "encouragement"},
  {"id": "e66", "text": "It is our choices that show what we truly are, far more than our abilities.", "author": "J. K. Rowling", "category": "encouragement"},
  {"id": "e67", "text": "Rock bottom became the solid foundation on which I rebuilt my life.", "author": "J. K. Rowling", "category": "encouragement"},
  {"id": "e68", "text": "The pessimist sees difficulty in every opportunity. The optimist sees opportunity in every difficulty.", "author": "Winston Churchill", "category": "encouragement"},
  {"id": "e69", "text": "You must be the change you wish to see in the world.", "author": "Mahatma Gandhi", "category": "encouragement"},
  {"id": "e70", "text": "Strength does not come from physical capacity. It comes from an indomitable will.", "author": "Mahatma Gandhi", "category": "encouragement"},
  {"id": "e71", "text": "Live as if you were to die tomorrow. Learn as if you were to live forever.", "author": "Mahatma Gandhi", "category": "encouragement"},
  {"id": "e72", "text": "Twenty years from now you will be more disappointed by the things that you didn't do than by the ones you did do.", "author": "H. Jackson Brown Jr.", "category": "encouragement"},
  {"id": "e73", "text": "The mind is everything. What you think you become.", "author": "Buddha", "category": "encouragement"},
  {"id": "e74", "text": "No matter how hard the past, you can always begin again.", "author": "Jack Kornfield", "category": "encouragement"},
  {"id": "e75", "text": "Out of difficulties grow miracles.", "author": "Jean de La Bruyère", "category": "encouragement"},
  {"id": "e76", "text": "Hope is the thing with feathers that perches in the soul.", "author": "Emily Dickinson", "category": "encouragement"},
  {"id": "e77", "text": "Not all those who wander are lost.", "author": "J. R. R. Tolkien", "category": "encouragement"},
  {"id": "e78", "text": "Even the darkest night will end and the sun will rise.", "author": "Victor Hugo", "category": "encouragement"},
  {"id": "e79", "text": "There is nothing like a dream to create the future.", "author": "Victor Hugo", "category": "encouragement"},
  {"id": "e80", "text": "All our dreams can come true, if we have the courage to pursue them.", "author": "Walt Disney", "category": "encouragement"},
  {"id": "e81", "text": "Courage is resistance to fear, mastery of fear, not absence of fear.", "author": "Mark Twain", "category": "encouragement"},
  {"id": "e82", "text": "The two most important days in your life are the day you are born and the day you find out why.", "author": "Mark Twain", "category": "encouragement"},
  {"id": "e83", "text": "Shoot for the moon. Even if you miss, you'll land among the stars.", "author": "Norman Vincent Peale", "category": "encouragement"},
  {"id": "e84", "text": "Change your thoughts and you change your world.", "author": "Norman Vincent Peale", "category": "encouragement"},
  {"id": "e85", "text": "Only in the darkness can you see the stars.", "author": "Martin Luther King Jr.", "category": "encouragement"},
  {"id": "e86", "text": "If you want to lift yourself up, lift up someone else.", "author": "Booker T. Washington", "category": "encouragement"},
  {"id": "e87", "text": "Success is the sum of small efforts, repeated day in and day out.", "author": "Robert Collier", "category": "encouragement"},
  {"id": "e88", "text": "The man who moves a mountain begins by carrying away small stones.", "author": "Confucius", "category": "encouragement"},
  {"id": "e89", "text": "Our greatest weakness lies in giving up. The most certain way to succeed is always to try just one more time.", "author": "Thomas Edison", "category": "encouragement"},
  {"id": "e90", "text": "I have not failed. I've just found 10,000 ways that won't work.", "author": "Thomas Edison", "category": "encouragement"},
  {"id": "e91", "text": "Many of life's failures are people who did not realize how close they were to success when they gave up.", "author": "Thomas Edison", "category": "encouragement"},
  {"id": "e92", "text": "You never know how strong you are until being strong is your only choice.", "author": "Bob Marley", "category": "encouragement"},
  {"id": "e93", "text": "When it rains, look for rainbows. When it's dark, look for stars.", "author": "Unknown", "category": "encouragement"},
  {"id": "e94", "text": "You are stronger than you know.", "author": "Unknown", "category": "encouragement"},
  {"id": "e95", "text": "One day at a time.", "author": "Unknown", "category": "encouragement"},
  {"id": "e96", "text": "The comeback is always stronger than the setback.", "author": "Unknown", "category": "encouragement"},
  {"id": "e97", "text": "Doubt kills more dreams than failure ever will.", "author": "Suzy Kassem", "category": "encouragement"},
  {"id": "e98", "text": "What we achieve inwardly will change outer reality.", "author": "Plutarch", "category": "encouragement"},
  {"id": "e99", "text": "However difficult life may seem, there is always something you can do and succeed at.", "author": "Stephen Hawking", "category": "encouragement"},
  {"id": "e100", "text": "At the end of the day, we can endure much more than we think we can.", "author": "Frida Kahlo", "category": "encouragement"}
]
